Topsis_Sanyam_102303059/__init__.py
Topsis_Sanyam_102303059/topsis.py
topsis_sanyam_102303059-1.0.1.dist-info/licenses/LICENSE
topsis_sanyam_102303059-1.0.1.dist-info/METADATA
topsis_sanyam_102303059-1.0.1.dist-info/WHEEL
topsis_sanyam_102303059-1.0.1.dist-info/top_level.txt
topsis_sanyam_102303059-1.0.1.dist-info/RECORD
