Metadata-Version: 2.4
Name: Topsis_Sanyam_102303059
Version: 1.0.1
Summary: A Python package for TOPSIS (Technique for Order of Preference by Similarity to Ideal Solution) analysis.
Home-page: https://github.com/SanyamWadhwa07/topsis_Sanyam_102303059
Author: Sanyam Wadhwa
Author-email: Sanyam Wadhwa <sanyamwadhwa.in@gmail.com>
License: MIT License
Classifier: Programming Language :: Python :: 3
Classifier: License :: OSI Approved :: MIT License
Classifier: Operating System :: OS Independent
Requires-Python: >=3.6
License-File: LICENSE
Dynamic: author
Dynamic: home-page
Dynamic: license-file
Dynamic: requires-python
